README.md
setup.py
hwinfos/__init__.py
hwinfos/myfunctions.py
hwinfos.egg-info/PKG-INFO
hwinfos.egg-info/SOURCES.txt
hwinfos.egg-info/dependency_links.txt
hwinfos.egg-info/top_level.txt