Metadata-Version: 2.1
Name: hwinfos
Version: 0.1.0
Summary: Get PC hardware info for Windows OS
Home-page: UNKNOWN
Author: R3FL3X
Author-email: christos.daglaroglou@gmail.com
License: MIT
Platform: UNKNOWN
Classifier: Programming Language :: Python
Classifier: Operating System :: Microsoft :: Windows
